{
  "schemaVersion": "1.0.0",
  "projectId": 1,
  "config": {
    "id": 1,
    "name": "test-project-areeb",
    "version": "1.0.0",
    "mainComponentId": "nzZNSXkPwOPpQ079N-3qq",
    "locale": "en",
    "globalErrorType": "INLINE",
    "showWidgetError": true,
    "showWidgetSuccess": true,
    "autoHideMessage": false,
    "closeableMessage": true,
    "theme": "",
    "securityConfigurations": [],
    "updatedTimestamp": "2022-07-04T17:10:15+05:00",
    "autoHideDuration": 10,
    "components": [],
    "triggers": [],
    "assets": []
  }
}
